ecvrf/__init__.py
ecvrf/hash_to_curve.py
ecvrf/key_management.py
ecvrf/proof_generation.py
ecvrf/proof_verification.py
ecvrf/utils.py
python_ecvrf_4o-0.1.1.dist-info/LICENSE
python_ecvrf_4o-0.1.1.dist-info/METADATA
python_ecvrf_4o-0.1.1.dist-info/WHEEL
python_ecvrf_4o-0.1.1.dist-info/top_level.txt
python_ecvrf_4o-0.1.1.dist-info/RECORD
